Moon/__init__.py
Moon/build.properties
Moon/build.py
Moon/requirements.toml
Moon/requirements.txt
Moon/__pycache__/__init__.cpython-311.pyc
Moon/__pycache__/__init__.cpython-313.pyc
Moon/data/fonts/GNF.ttf
Moon/data/icons/default_app_icon.png
Moon/data/icons/logo.png
Moon/data/ui/close.png
Moon/data/ui/fliper.png
Moon/data/ui/resize.png
Moon/dlls/Moon.dll
Moon/dlls/openal32.dll
Moon/python/Audio.py
Moon/python/Colors.py
Moon/python/Inputs.py
Moon/python/Math.py
Moon/python/Process.py
Moon/python/Time.py
Moon/python/Types.py
Moon/python/Vectors.py
Moon/python/Views.py
Moon/python/Window.py
Moon/python/__init__.py
Moon/python/utils.py
Moon/python/Engine/BoxColliders.py
Moon/python/Engine/Camera.py
Moon/python/Engine/ParticleSystem.py
Moon/python/Engine/Tilesets.py
Moon/python/Engine/__pycache__/BoxColliders.cpython-313.pyc
Moon/python/Engine/__pycache__/Camera.cpython-313.pyc
Moon/python/Engine/__pycache__/Colliders.cpython-313.pyc
Moon/python/Engine/__pycache__/ParticleEffects.cpython-313.pyc
Moon/python/Engine/__pycache__/ParticleSystem.cpython-313.pyc
Moon/python/Engine/__pycache__/Tilesets.cpython-313.pyc
Moon/python/Rendering/Drawable.py
Moon/python/Rendering/RenderStates.py
Moon/python/Rendering/Shaders.py
Moon/python/Rendering/Shapes.py
Moon/python/Rendering/Sprites.py
Moon/python/Rendering/Text.py
Moon/python/Rendering/Vertexes.py
Moon/python/Rendering/__pycache__/Drawable.cpython-313.pyc
Moon/python/Rendering/__pycache__/RenderStates.cpython-313.pyc
Moon/python/Rendering/__pycache__/Shaders.cpython-313.pyc
Moon/python/Rendering/__pycache__/Shapes.cpython-313.pyc
Moon/python/Rendering/__pycache__/Sprites.cpython-313.pyc
Moon/python/Rendering/__pycache__/Text.cpython-313.pyc
Moon/python/Rendering/__pycache__/Vertexes.cpython-313.pyc
Moon/python/__pycache__/Audio.cpython-313.pyc
Moon/python/__pycache__/Colors.cpython-313.pyc
Moon/python/__pycache__/Inputs.cpython-313.pyc
Moon/python/__pycache__/Math.cpython-313.pyc
moonframework-0.1.21.dist-info/METADATA
moonframework-0.1.21.dist-info/WHEEL
moonframework-0.1.21.dist-info/top_level.txt
moonframework-0.1.21.dist-info/RECORD
